lafs-0.0.5.dist-info/METADATA
lafs-0.0.5.dist-info/WHEEL
lafs-0.0.5.dist-info/licenses/LICENSE
lafs/__init__.py
lafs/lafs.cp39-win_amd64.pyd
lafs-0.0.5.dist-info/RECORD
