Metadata-Version: 2.4
Name: lafs
Version: 0.0.5
Classifier: Development Status :: 3 - Alpha
Classifier: Intended Audience :: Developers
Classifier: License :: DFSG approved
Classifier: License :: OSI Approved
Classifier: License :: OSI Approved :: MIT License
Classifier: Natural Language :: English
Classifier: Programming Language :: Python
Classifier: Programming Language :: Python :: 3
Classifier: Programming Language :: Python :: 3.9
Classifier: Programming Language :: Python :: 3.10
Classifier: Programming Language :: Python :: 3.11
Classifier: Programming Language :: Python :: 3.12
Classifier: Programming Language :: Python :: 3 :: Only
Classifier: Programming Language :: Python :: Implementation :: CPython
Classifier: Programming Language :: Python :: Implementation :: PyPy
Classifier: Programming Language :: Rust
Classifier: Topic :: Security :: Cryptography
License-File: LICENSE
Summary: Least-Authority File Store utils
Keywords: allmydata,tahoe-lafs,tahoe,lafs
Author-email: "Christopher R. Wood" <chris@cyberethics.ca>
Requires-Python: >=3.9
Project-URL: Issues, https://github.com/crwood/lafs/issues
Project-URL: Source, https://github.com/crwood/lafs
